nbresult/__init__.py
nbresult-0.1.1.dist-info/LICENSE
nbresult-0.1.1.dist-info/METADATA
nbresult-0.1.1.dist-info/WHEEL
nbresult-0.1.1.dist-info/top_level.txt
nbresult-0.1.1.dist-info/RECORD
