Metadata-Version: 2.2
Name: nbresult
Version: 0.1.1
Summary: Extract results from Jupyter notebooks
Home-page: https://github.com/lewagon/nbresult
Author: Kevin Robert
Author-email: kevin@lewagon.org
License: MIT
License-File: LICENSE
Dynamic: author
Dynamic: author-email
Dynamic: description
Dynamic: description-content-type
Dynamic: home-page
Dynamic: license
Dynamic: summary
